LICENSE
pyproject.toml
readme.md
setup.py
./readme.md
./data/ConfigOnlyLoader.default.data.yaml
./data/ConfigOnlyLoader.ssh_dst_group.data.yaml
./docs/readme.md
./docs/dev_notes/brief_history.md
./docs/dev_notes/code_style.md
./docs/dev_notes/completion_notes.md
./docs/dev_notes/completion_perf_notes.md
./docs/dev_notes/docker_notes.md
./docs/dev_notes/enum_language.md
./docs/dev_notes/gui_cypress_tests_notes.md
./docs/dev_notes/how_search_works.md
./docs/dev_notes/library_vs_framework.md
./docs/dev_notes/mongo_notes.md
./docs/dev_notes/project_origin.md
./docs/dev_notes/query_perf_10_x_more_data_notes.md
./docs/dev_notes/query_perf_cache_vs_no_cache.md
./docs/dev_notes/query_perf_mongomock_notes.md
./docs/dev_notes/query_perf_pymongo_notes.md
./docs/dev_notes/release_procedure.md
./docs/dev_notes/reversed_naming_order.md
./docs/dev_notes/screencast_notes.md
./docs/dev_notes/semver_notes.md
./docs/dev_notes/term_dictionary.md
./docs/dev_notes/version_format.md
./docs/feature_stories/FS_00_13_77_97.plugin_framework.md
./docs/feature_stories/FS_01_89_09_24.interp_tree.md
./docs/feature_stories/FS_02_25_41_81.func_id_query_enum_items.md
./docs/feature_stories/FS_06_99_43_60.array_prop_value.md
./docs/feature_stories/FS_07_10_10_74.relay_to_another_server.md
./docs/feature_stories/FS_08_58_30_24.incomplete_arg.md
./docs/feature_stories/FS_10_93_78_10.arg_name_to_prop_name_map.md
./docs/feature_stories/FS_11_87_76_73.highlight_tangent_prefix.md
./docs/feature_stories/FS_13_51_07_97.singled_out_implicit_values.md
./docs/feature_stories/FS_14_59_14_06.pending_requests.md
./docs/feature_stories/FS_15_79_76_85.line_processor.md
./docs/feature_stories/FS_16_07_78_84.conf_dir_priority.md
./docs/feature_stories/FS_18_64_57_18.function_with_indefinite_input_data_envelopes_like_varargs.md
./docs/feature_stories/FS_20_88_05_60.dictated_arg.md
./docs/feature_stories/FS_23_62_89_43.tangent_token.md
./docs/feature_stories/FS_26_43_73_72.func_tree.md
argrelay.egg-info/PKG-INFO
argrelay.egg-info/SOURCES.txt
argrelay.egg-info/dependency_links.txt
argrelay.egg-info/requires.txt
argrelay.egg-info/top_level.txt
