Metadata-Version: 2.4
Name: argrelay
Version: 0.8.1
Summary: A data server to CLI tools with attribute search & Tab-completion in Bash shell
Home-page: https://github.com/argrelay/argrelay
Author: uvsmtid
Author-email: uvsmtid@gmail.com
Project-URL: Bug Tracker, https://github.com/argrelay/argrelay/issues
Keywords: argparse,argcomplete,bash,complete
Classifier: Development Status :: 3 - Alpha
Classifier: Environment :: Console
Classifier: Framework :: Flask
Classifier: Intended Audience :: Information Technology
Classifier: Topic :: Terminals
Classifier: Topic :: System :: Shells
Classifier: Topic :: Scientific/Engineering :: Human Machine Interfaces
Classifier: Topic :: Text Processing :: Indexing
Classifier: Topic :: Internet :: WWW/HTTP :: Indexing/Search
Classifier: Topic :: Internet :: WWW/HTTP :: HTTP Servers
Classifier: Programming Language :: Python :: 3
Classifier: License :: OSI Approved :: Apache Software License
Classifier: Operating System :: POSIX :: Linux
Requires-Python: >=3.9
License-File: LICENSE
Requires-Dist: Flask
Requires-Dist: Werkzeug
Requires-Dist: PyYaml
Requires-Dist: jsonschema
Requires-Dist: flasgger
Requires-Dist: marshmallow<4.0.0
Requires-Dist: marshmallow-oneofschema
Requires-Dist: apispec
Requires-Dist: pymongo
Requires-Dist: GitPython
Requires-Dist: mongomock
Requires-Dist: requests
Requires-Dist: cachetools
Provides-Extra: tests
Requires-Dist: tox; extra == "tests"
Requires-Dist: responses; extra == "tests"
Requires-Dist: mongomock; extra == "tests"
Requires-Dist: pandas; extra == "tests"
Requires-Dist: icecream; extra == "tests"
Requires-Dist: jsonpath-ng; extra == "tests"
Requires-Dist: import-linter; extra == "tests"
Dynamic: author
Dynamic: author-email
Dynamic: classifier
Dynamic: description
Dynamic: description-content-type
Dynamic: home-page
Dynamic: keywords
Dynamic: license-file
Dynamic: project-url
Dynamic: provides-extra
Dynamic: requires-dist
Dynamic: requires-python
Dynamic: summary
